_xbrz.cpython-36m-aarch64-linux-gnu.so
xbrz.py
xbrz.py-1.0.2.dist-info/METADATA
xbrz.py-1.0.2.dist-info/RECORD
xbrz.py-1.0.2.dist-info/LICENSE.md
xbrz.py-1.0.2.dist-info/WHEEL
xbrz.py-1.0.2.dist-info/top_level.txt
