Metadata-Version: 2.1
Name: xbrz.py
Version: 1.0.2
Summary: ctypes-based binding library for the xBRZ pixel-art image scaling algorithm
Home-page: https://github.com/iomintz/xbrz.py
Author: iomintz
Author-email: io@mintz.cc
License: AGPL-3.0-or-later
Platform: UNKNOWN
Classifier: Topic :: Software Development
Classifier: License :: OSI Approved :: GNU Affero General Public License v3 or later (AGPLv3+)
Classifier: Development Status :: 5 - Production/Stable
Classifier: Programming Language :: Python :: 3 :: Only
Classifier: Programming Language :: Python :: 3.6
Classifier: Programming Language :: Python :: 3.7
Classifier: Programming Language :: Python :: 3.8
Classifier: Programming Language :: C++
Classifier: Topic :: Multimedia :: Graphics
Requires-Python: >=3.6.0
Provides-Extra: pillow
Requires-Dist: Pillow (<8.0.0,>=7.1.2) ; extra == 'pillow'
Provides-Extra: wand
Requires-Dist: Wand (<1.0.0,>=0.6.1) ; extra == 'wand'
